<?xml version="1.0" encoding="utf-8" ?>
<Defs>
  <ThingDef ParentName="BuildingBase">
    <defName>Column_Glowing</defName>
    <label>glowing column</label>
    <description>A column capable of holding a roof. Does not block sight or movement and looks quite nice. Emits light (blue by default). Color can be changed after researching Colored lights.</description>
    <designationCategory>Structure</designationCategory>
    <uiOrder>2041</uiOrder>
    <altitudeLayer>Building</altitudeLayer>
    <passability>PassThroughOnly</passability>
    <fillPercent>0.25</fillPercent>
    <pathCost>0</pathCost>
    <uiIconScale>1.2</uiIconScale>
    <statBases>
      <MaxHitPoints>1000</MaxHitPoints>
      <WorkToBuild>7500</WorkToBuild>
      <Mass>15</Mass>
      <Flammability>0</Flammability>
      <Beauty>100</Beauty>
      <StyleDominance MayRequire="Ludeon.RimWorld.Ideology">10</StyleDominance>
    </statBases>
    <stuffCategories>
      <li>Metallic</li>
      <li>Stony</li>
    </stuffCategories>
    <costStuffCount>100</costStuffCount>
    <holdsRoof>true</holdsRoof>
    <canOverlapZones>false</canOverlapZones>
    <rotatable>false</rotatable>
    <fertility>0</fertility>
    <specialDisplayRadius>6.9</specialDisplayRadius> <!-- must be kept in sync with roof hold-up radius -->
    <building>
      <isInert>true</isInert>
      <ai_chillDestination>false</ai_chillDestination>
      <paintable>true</paintable>
      <buildingTags>
        <li>Column</li>
      </buildingTags>
    </building>
    <graphicData>
      <drawSize>(0.5,1.25)</drawSize>
      <drawOffset>(0,0,0.2)</drawOffset>
      <texPath>Things/Building/Furniture/Column_GT</texPath>
      <graphicClass>Graphic_Single</graphicClass>
      <shadowData>
        <volume>(0.3, 0.5, 0.3)</volume>
        <offset>(0,0,-0.23)</offset>
      </shadowData>
      <damageData>
        <rect>(0.2,0.2,0.6,0.6)</rect>
      </damageData>
    </graphicData>
    <researchPrerequisites>
      <li>MetalFab</li>
    </researchPrerequisites>
    <placeWorkers>
      <li>PlaceWorker_GlowRadius</li>
    </placeWorkers>
    <comps>
      <li Class="CompProperties_Power">
        <compClass>CompPowerTrader</compClass>
        <basePowerConsumption>30</basePowerConsumption>
        <powerUpgrades>
          <li>
            <researchProject>ColoredLights</researchProject>
            <factor>0.5</factor>
          </li>
          <li>
            <researchProject>PowerEfficiency_II</researchProject>
            <factor>0.333</factor>
          </li>
        </powerUpgrades>
      </li>
      <li Class="CompProperties_Styleable"/>
      <li Class="CompProperties_Glower">
        <glowRadius>12</glowRadius>
        <glowColor>(80,130,255,0)</glowColor>
        <!-- default soft blue -->
        <colorPickerEnabled>true</colorPickerEnabled>
        <darklightToggle>true</darklightToggle>
      </li>
    </comps>
  </ThingDef>
</Defs>